py_lib3mf/Lib3MF.py
py_lib3mf/__init__.py
py_lib3mf/lib3mf.dll
py_lib3mf/lib3mf.dylib
py_lib3mf/lib3mf.so
py_lib3mf/lib3mf.x86_64.dylib
py_lib3mf-2.2.0.dist-info/METADATA
py_lib3mf-2.2.0.dist-info/WHEEL
py_lib3mf-2.2.0.dist-info/top_level.txt
py_lib3mf-2.2.0.dist-info/RECORD
