Metadata-Version: 2.1
Name: py-lib3mf
Version: 2.2.0
Summary: A python package for Lib3MF tools
License: Apache-2.0
Requires-Python: >=3.9
